src/__init__.py
src/main.py
loadavg-1.9.0.dist-info/METADATA
loadavg-1.9.0.dist-info/WHEEL
loadavg-1.9.0.dist-info/entry_points.txt
loadavg-1.9.0.dist-info/top_level.txt
loadavg-1.9.0.dist-info/RECORD
